m.py
runner.py
rusgramm-0.1.1.dist-info/licenses/LICENSE
rusgramm-0.1.1.dist-info/METADATA
rusgramm-0.1.1.dist-info/WHEEL
rusgramm-0.1.1.dist-info/entry_points.txt
rusgramm-0.1.1.dist-info/tmp3nxgsmmi
rusgramm-0.1.1.dist-info/tmp7xvxnuw8
rusgramm-0.1.1.dist-info/tmpa9_7b5pl
rusgramm-0.1.1.dist-info/tmpbn7lsum1
rusgramm-0.1.1.dist-info/tmpkudeqfob
rusgramm-0.1.1.dist-info/tmplp_6zueu
rusgramm-0.1.1.dist-info/tmpt_1jlk9f
rusgramm-0.1.1.dist-info/tmpta4_puej
rusgramm-0.1.1.dist-info/tmpupg384vl
rusgramm-0.1.1.dist-info/top_level.txt
rusgramm-0.1.1.dist-info/RECORD
